wflite/__init__.py
wflite/serverless.py
wflite/cli/__init__.py
wflite/cli/workflow_cli.py
wflite/config/__init__.py
wflite/config/azure_keyvault.py
wflite/config/config_loader.py
wflite/core/__init__.py
wflite/core/statemachine_builder.py
wflite/core/statemachine_core.py
wflite/core/statemachine_repository.py
wflite/core/visualization.py
wflite/domain/__init__.py
wflite/models/__init__.py
wflite/models/db_models.py
wflite/parsers/__init__.py
wflite/parsers/lucid_converter.py
wflite/persistence/__init__.py
wflite/persistence/cosmosdb_provider.py
wflite/persistence/dynamodb_provider.py
wflite/persistence/mongodb_provider.py
wflite/persistence/provider_factory.py
wflite/persistence/sqlite_provider.py
wflite/registry/__init__.py
wflite/registry/customer_manager.py
wflite/registry/db_registry.py
wflite/registry/repository_mock.py
wflite/runtime/__init__.py
wflite/runtime/handlers.py
wflite/runtime/serverless.py
wflite/runtime/statemachine_api.py
wflite/runtime/statemachine_runtime.py
wflite/runtime/workflow_api.py
wflite/tools/__init__.py
wflite/tools/import_template.py
wflite/tools/lucid_converter.py
wflite/tools/migrate_table_name.py
wflite/tools/paths.py
wflite/tools/template_validator.py
wflite/visualization/__init__.py
wflite/visualization/state_machine_viz.py
wflite-0.0.42.dist-info/METADATA
wflite-0.0.42.dist-info/WHEEL
wflite-0.0.42.dist-info/entry_points.txt
wflite-0.0.42.dist-info/top_level.txt
wflite-0.0.42.dist-info/RECORD
