Metadata-Version: 2.2
Name: wflite
Version: 0.0.42
Summary: Workflow Lite: A lightweight workflow engine
Author: Jean-Paul Buu-Sao
Author-email: jbuusao@jgmail.com
Requires-Dist: requests
Requires-Dist: pydantic
Requires-Dist: python-dotenv
Provides-Extra: azure
Requires-Dist: azure-identity; extra == "azure"
Requires-Dist: azure-keyvault-secrets; extra == "azure"
Dynamic: author
Dynamic: author-email
Dynamic: description
Dynamic: description-content-type
Dynamic: provides-extra
Dynamic: requires-dist
Dynamic: summary
